LICENSE.md
README.md
buscolite/__init__.py
buscolite/__main__.py
buscolite/augustus.py
buscolite/busco.py
buscolite/fasta.py
buscolite/fastx.py
buscolite/gff.py
buscolite/help_formatter.py
buscolite/log.py
buscolite/search.py
buscolite/utilities.py
buscolite/data/EOG092C0B3U.prfl
buscolite/data/HsDHC.prfl
buscolite/data/busco_test.fa
buscolite/data/example.fa
buscolite-25.4.24.dist-info/METADATA
buscolite-25.4.24.dist-info/WHEEL
buscolite-25.4.24.dist-info/entry_points.txt
buscolite-25.4.24.dist-info/licenses/LICENSE.md
buscolite-25.4.24.dist-info/RECORD
