Metadata-Version: 2.4
Name: buscolite
Version: 25.4.24
Summary: busco analysis for gene predictions
Project-URL: Homepage, https://github.com/nextgenusfs/buscolite
Project-URL: Repository, https://github.com/nextgenusfs/buscolite.git
Author-email: Jon Palmer <nextgenusfs@gmail.com>
License: BSD 2-Clause License
License-File: LICENSE.md
Keywords: BUSCO,annotation,bioinformatics,completeness,genome
Classifier: Development Status :: 4 - Beta
Classifier: Intended Audience :: Science/Research
Classifier: License :: OSI Approved :: BSD License
Classifier: Operating System :: Unix
Classifier: Programming Language :: Python
Classifier: Topic :: Scientific/Engineering :: Bio-Informatics
Requires-Python: >=3.6.0
Requires-Dist: natsort
Requires-Dist: packaging
Requires-Dist: pyfastx>=2.0.0
Requires-Dist: pyhmmer>=0.10.15
Provides-Extra: dev
Requires-Dist: black>=24.3.0; extra == 'dev'
Requires-Dist: flake8>=7.0.0; extra == 'dev'
Requires-Dist: isort>=5.13.2; extra == 'dev'
Requires-Dist: pre-commit>=3.5.0; extra == 'dev'
Requires-Dist: pytest-cov>=4.1.0; extra == 'dev'
Requires-Dist: pytest>=7.4.0; extra == 'dev'
